pypool_pump/__init__.py
pypool_pump/__version__.py
pypool_pump/run.py
pypool_pump/__pycache__/__init__.cpython-37.pyc
pypool_pump/__pycache__/__version__.cpython-37.pyc
pypool_pump/__pycache__/run.cpython-37.pyc
pypool_pump-0.0.1.dist-info/LICENSE
pypool_pump-0.0.1.dist-info/METADATA
pypool_pump-0.0.1.dist-info/WHEEL
pypool_pump-0.0.1.dist-info/top_level.txt
pypool_pump-0.0.1.dist-info/RECORD
