Metadata-Version: 2.1
Name: pypool-pump
Version: 0.0.1
Summary: Calculate pool filtering pump duration and schedule
Home-page: https://github.com/oncleben31/pypool-pump
Author: Oncleben31
Author-email: oncleben31@gmail.com
License: MIT
Platform: UNKNOWN
Classifier: License :: OSI Approved :: MIT License
Classifier: Programming Language :: Python
Classifier: Programming Language :: Python :: 3
